MANIFEST.in
README.rst
setup.py
spyral/__init__.py
spyral/_style.py
spyral/actor.py
spyral/animation.py
spyral/clock.py
spyral/compat.py
spyral/core.py
spyral/debug.py
spyral/dev.py
spyral/director.py
spyral/easing.py
spyral/event.py
spyral/exceptions.py
spyral/font.py
spyral/form.py
spyral/image.py
spyral/keyboard.py
spyral/layertree.py
spyral/memoize.py
spyral/mouse.py
spyral/rect.py
spyral/scene.py
spyral/sprite.py
spyral/util.py
spyral/vector.py
spyral/view.py
spyral/weakmethod.py
spyral/widgets.py
spyral.egg-info/PKG-INFO
spyral.egg-info/SOURCES.txt
spyral.egg-info/dependency_links.txt
spyral.egg-info/requires.txt
spyral.egg-info/top_level.txt
spyral/resources/default_key_mappings.txt
spyral/resources/form_defaults.spys
spyral/resources/style.parsley
spyral/resources/theme.cfg
spyral/resources/fonts/AUTHORS
spyral/resources/fonts/BUGS
spyral/resources/fonts/DejaVuSans.ttf
spyral/resources/fonts/README
spyral/resources/images/README
spyral/resources/images/Thumbs.db
spyral/resources/images/button.down.focused.png
spyral/resources/images/button.down.hovered.png
spyral/resources/images/button.down.png
spyral/resources/images/button.up.focused.png
spyral/resources/images/button.up.hovered.png
spyral/resources/images/button.up.png
spyral/resources/images/check.down.hovered.png
spyral/resources/images/check.down.png
spyral/resources/images/check.up.hovered.png
spyral/resources/images/check.up.png
spyral/resources/images/input.focused.png
spyral/resources/images/input.unfocused.png
spyral/resources/images/radio.off.hovered.png
spyral/resources/images/radio.off.png
spyral/resources/images/radio.on.hovered.png
spyral/resources/images/radio.on.png