Metadata-Version: 1.1
Name: spyral
Version: 0.9.6
Summary: A Python library for game development
Home-page: https://github.com/platipy/spyral
Author: Platipy Project
Author-email: platipy@platipy.org
License: LGPLv2
Keywords: pygame game engine
Platform: UNKNOWN
Classifier: Development Status :: 5 - Production/Stable
Classifier: Intended Audience :: Developers
Classifier: Intended Audience :: Education
Classifier: License :: OSI Approved :: GNU Lesser General Public License v2 (LGPLv2)
Classifier: Operating System :: Microsoft :: Windows
Classifier: Operating System :: MacOS :: MacOS X
Classifier: Operating System :: POSIX :: Linux
Classifier: Programming Language :: Python :: 2 :: Only
Classifier: Topic :: Games/Entertainment
Classifier: Topic :: Multimedia
Classifier: Topic :: Software Development
Classifier: Topic :: Software Development :: Libraries :: pygame
